[
  {
    "@id": "mailto:remko.nijzink@list.lu",
    "@type": "Person",
    "@version": 1,
    "affiliation": null,
    "alternate_name": null,
    "email": "remko.nijzink@list.lu",
    "label": "nijzink",
    "name": "nijzink"
  },
  {
    "@id": "https://github.com/swissdatasciencecenter/renku-python/tree/v0.12.3.dev24",
    "@type": "SoftwareAgent",
    "@version": 1,
    "label": "renku 0.12.3.dev24"
  },
  {
    "@id": "https://github.com/runs/a43f2254d4ce6a7b26ab6b900d5a083dd9cfae61/arguments/10",
    "@type": "CommandArgument",
    "@version": 1,
    "label": "Command Argument \"1\"",
    "position": 10,
    "prefix": null,
    "value": "1"
  },
  {
    "@id": "https://github.com/runs/a43f2254d4ce6a7b26ab6b900d5a083dd9cfae61/arguments/11",
    "@type": "CommandArgument",
    "@version": 1,
    "label": "Command Argument \"1\"",
    "position": 11,
    "prefix": null,
    "value": "1"
  },
  {
    "@id": "https://github.com/runs/a43f2254d4ce6a7b26ab6b900d5a083dd9cfae61/arguments/12",
    "@type": "CommandArgument",
    "@version": 1,
    "label": "Command Argument \"0\"",
    "position": 12,
    "prefix": null,
    "value": "0"
  },
  {
    "@id": "https://github.com/runs/a43f2254d4ce6a7b26ab6b900d5a083dd9cfae61/arguments/13",
    "@type": "CommandArgument",
    "@version": 1,
    "label": "Command Argument \"1\"",
    "position": 13,
    "prefix": null,
    "value": "1"
  },
  {
    "@id": "https://github.com/runs/a43f2254d4ce6a7b26ab6b900d5a083dd9cfae61/arguments/16",
    "@type": "CommandArgument",
    "@version": 1,
    "label": "Command Argument \"o\"",
    "position": 16,
    "prefix": "-e",
    "value": "o"
  },
  {
    "@id": "https://github.com/runs/a43f2254d4ce6a7b26ab6b900d5a083dd9cfae61/arguments/18",
    "@type": "CommandArgument",
    "@version": 1,
    "label": "Command Argument \"o\"",
    "position": 18,
    "prefix": "-a",
    "value": "o"
  },
  {
    "@id": "https://github.com/runs/a43f2254d4ce6a7b26ab6b900d5a083dd9cfae61/arguments/20",
    "@type": "CommandArgument",
    "@version": 1,
    "label": "Command Argument \"src/VOM/VOM_fortran/VOM-code/*\"",
    "position": 20,
    "prefix": "-c ",
    "value": "src/VOM/VOM_fortran/VOM-code/*"
  },
  {
    "@id": "https://github.com/runs/a43f2254d4ce6a7b26ab6b900d5a083dd9cfae61/arguments/4",
    "@type": "CommandArgument",
    "@version": 1,
    "label": "Command Argument \"5\"",
    "position": 4,
    "prefix": "-p ",
    "value": "5"
  },
  {
    "@id": "https://github.com/runs/a43f2254d4ce6a7b26ab6b900d5a083dd9cfae61/arguments/5",
    "@type": "CommandArgument",
    "@version": 1,
    "label": "Command Argument \"p\"",
    "position": 5,
    "prefix": "-o",
    "value": "p"
  },
  {
    "@id": "https://github.com/runs/a43f2254d4ce6a7b26ab6b900d5a083dd9cfae61/arguments/6",
    "@type": "CommandArgument",
    "@version": 1,
    "label": "Command Argument \"1\"",
    "position": 6,
    "prefix": null,
    "value": "1"
  },
  {
    "@id": "https://github.com/runs/a43f2254d4ce6a7b26ab6b900d5a083dd9cfae61/arguments/7",
    "@type": "CommandArgument",
    "@version": 1,
    "label": "Command Argument \"1\"",
    "position": 7,
    "prefix": null,
    "value": "1"
  },
  {
    "@id": "https://github.com/runs/a43f2254d4ce6a7b26ab6b900d5a083dd9cfae61/arguments/8",
    "@type": "CommandArgument",
    "@version": 1,
    "label": "Command Argument \"1\"",
    "position": 8,
    "prefix": null,
    "value": "1"
  },
  {
    "@id": "https://github.com/runs/a43f2254d4ce6a7b26ab6b900d5a083dd9cfae61/arguments/9",
    "@type": "CommandArgument",
    "@version": 1,
    "label": "Command Argument \"1\"",
    "position": 9,
    "prefix": null,
    "value": "1"
  },
  {
    "@id": "https://github.com/plans/a43f2254d4ce6a7b26ab6b900d5a083dd9cfae61/outputs/3",
    "@type": "CommandOutputTemplate",
    "@version": 1,
    "create_folder": false,
    "label": "Command Output Template \"data/VOM_output/DryRiver/nofreedrainage_cpcff2.0/beststats\"",
    "mapped_to": null,
    "position": 3,
    "prefix": "-o ",
    "produces": "data/VOM_output/DryRiver/nofreedrainage_cpcff2.0/beststats"
  },
  {
    "@id": "https://github.com/plans/a43f2254d4ce6a7b26ab6b900d5a083dd9cfae61/inputs/1",
    "@type": "CommandInputTemplate",
    "@version": 1,
    "consumes": "src_py/sce_stats.py",
    "label": "Command Input Template \"src_py/sce_stats.py\"",
    "mapped_to": null,
    "position": 1,
    "prefix": null
  },
  {
    "@id": "https://github.com/plans/a43f2254d4ce6a7b26ab6b900d5a083dd9cfae61/inputs/14",
    "@type": "CommandInputTemplate",
    "@version": 1,
    "consumes": "data/VOM_input/DryRiver/dailyweather.prn",
    "label": "Command Input Template \"data/VOM_input/DryRiver/dailyweather.prn\"",
    "mapped_to": null,
    "position": 14,
    "prefix": "-d "
  },
  {
    "@id": "https://github.com/plans/a43f2254d4ce6a7b26ab6b900d5a083dd9cfae61/inputs/15",
    "@type": "CommandInputTemplate",
    "@version": 1,
    "consumes": "work/DryRiver/nofreedrainage_cpcff2.0/best",
    "label": "Command Input Template \"work/DryRiver/nofreedrainage_cpcff2.0/best\"",
    "mapped_to": null,
    "position": 15,
    "prefix": "-w "
  },
  {
    "@id": "https://github.com/plans/a43f2254d4ce6a7b26ab6b900d5a083dd9cfae61/inputs/17",
    "@type": "CommandInputTemplate",
    "@version": 1,
    "consumes": "data/DINGO/Ea_dry.txt",
    "label": "Command Input Template \"data/DINGO/Ea_dry.txt\"",
    "mapped_to": null,
    "position": 17,
    "prefix": null
  },
  {
    "@id": "https://github.com/plans/a43f2254d4ce6a7b26ab6b900d5a083dd9cfae61/inputs/19",
    "@type": "CommandInputTemplate",
    "@version": 1,
    "consumes": "data/DINGO/GPPdaily_dry.txt",
    "label": "Command Input Template \"data/DINGO/GPPdaily_dry.txt\"",
    "mapped_to": null,
    "position": 19,
    "prefix": null
  },
  {
    "@id": "https://github.com/plans/a43f2254d4ce6a7b26ab6b900d5a083dd9cfae61/inputs/2",
    "@type": "CommandInputTemplate",
    "@version": 1,
    "consumes": "data/VOM_output/DryRiver/nofreedrainage_cpcff2.0/sce_out.txt",
    "label": "Command Input Template \"data/VOM_output/DryRiver/nofreedrainage_cpcff2.0/sce_out.txt\"",
    "mapped_to": null,
    "position": 2,
    "prefix": "-i "
  },
  {
    "@id": "https://github.com/plans/a43f2254d4ce6a7b26ab6b900d5a083dd9cfae61",
    "@type": "Plan",
    "@version": 1,
    "arguments": [
      {
        "@id": "https://github.com/runs/a43f2254d4ce6a7b26ab6b900d5a083dd9cfae61/arguments/10"
      },
      {
        "@id": "https://github.com/runs/a43f2254d4ce6a7b26ab6b900d5a083dd9cfae61/arguments/11"
      },
      {
        "@id": "https://github.com/runs/a43f2254d4ce6a7b26ab6b900d5a083dd9cfae61/arguments/12"
      },
      {
        "@id": "https://github.com/runs/a43f2254d4ce6a7b26ab6b900d5a083dd9cfae61/arguments/13"
      },
      {
        "@id": "https://github.com/runs/a43f2254d4ce6a7b26ab6b900d5a083dd9cfae61/arguments/16"
      },
      {
        "@id": "https://github.com/runs/a43f2254d4ce6a7b26ab6b900d5a083dd9cfae61/arguments/18"
      },
      {
        "@id": "https://github.com/runs/a43f2254d4ce6a7b26ab6b900d5a083dd9cfae61/arguments/20"
      },
      {
        "@id": "https://github.com/runs/a43f2254d4ce6a7b26ab6b900d5a083dd9cfae61/arguments/4"
      },
      {
        "@id": "https://github.com/runs/a43f2254d4ce6a7b26ab6b900d5a083dd9cfae61/arguments/5"
      },
      {
        "@id": "https://github.com/runs/a43f2254d4ce6a7b26ab6b900d5a083dd9cfae61/arguments/6"
      },
      {
        "@id": "https://github.com/runs/a43f2254d4ce6a7b26ab6b900d5a083dd9cfae61/arguments/7"
      },
      {
        "@id": "https://github.com/runs/a43f2254d4ce6a7b26ab6b900d5a083dd9cfae61/arguments/8"
      },
      {
        "@id": "https://github.com/runs/a43f2254d4ce6a7b26ab6b900d5a083dd9cfae61/arguments/9"
      }
    ],
    "command": "python3",
    "inputs": [
      {
        "@id": "https://github.com/plans/a43f2254d4ce6a7b26ab6b900d5a083dd9cfae61/inputs/1"
      },
      {
        "@id": "https://github.com/plans/a43f2254d4ce6a7b26ab6b900d5a083dd9cfae61/inputs/14"
      },
      {
        "@id": "https://github.com/plans/a43f2254d4ce6a7b26ab6b900d5a083dd9cfae61/inputs/15"
      },
      {
        "@id": "https://github.com/plans/a43f2254d4ce6a7b26ab6b900d5a083dd9cfae61/inputs/17"
      },
      {
        "@id": "https://github.com/plans/a43f2254d4ce6a7b26ab6b900d5a083dd9cfae61/inputs/19"
      },
      {
        "@id": "https://github.com/plans/a43f2254d4ce6a7b26ab6b900d5a083dd9cfae61/inputs/2"
      }
    ],
    "name": "python3-cb52a8505b064622b86c4ab45fca7eaa",
    "outputs": [
      {
        "@id": "https://github.com/plans/a43f2254d4ce6a7b26ab6b900d5a083dd9cfae61/outputs/3"
      }
    ],
    "success_codes": []
  },
  {
    "@id": "renku+0.3.4.dev13@datascience.ch",
    "@type": "SoftwareAgent",
    "@version": 1,
    "label": "renku 0.3.4.dev13"
  },
  {
    "@id": "https://github.com/activities/13fb7e0c-e003-44f5-ab78-51b462cc5352/association",
    "@type": "Association",
    "@version": 1,
    "agent": {
      "@id": "renku+0.3.4.dev13@datascience.ch"
    },
    "plan": {
      "@id": "https://github.com/plans/a43f2254d4ce6a7b26ab6b900d5a083dd9cfae61"
    }
  },
  {
    "@id": "https://github.com/blob/c97b3a4e0b6bc81ff62e1e501b285364eaf562e6/src_py/sce_stats.py",
    "@type": "Entity",
    "@version": 1,
    "checksum": "c97b3a4e0b6bc81ff62e1e501b285364eaf562e6",
    "path": "src_py/sce_stats.py"
  },
  {
    "@id": "https://github.com/activities/13fb7e0c-e003-44f5-ab78-51b462cc5352/usage/7d0ca139-33bb-4e9b-beec-ac57ca7f71aa/c97b3a4e0b6bc81ff62e1e501b285364eaf562e6/src_py/sce_stats.py",
    "@type": "Usage",
    "@version": 1,
    "entity": {
      "@id": "https://github.com/blob/c97b3a4e0b6bc81ff62e1e501b285364eaf562e6/src_py/sce_stats.py"
    },
    "role": "inputs/1"
  },
  {
    "@id": "https://github.com/blob/c0e6ea328bb5c54fabd78228dba135eb966917f8/data/VOM_input/DryRiver/dailyweather.prn",
    "@type": "Entity",
    "@version": 1,
    "checksum": "c0e6ea328bb5c54fabd78228dba135eb966917f8",
    "path": "data/VOM_input/DryRiver/dailyweather.prn"
  },
  {
    "@id": "https://github.com/activities/13fb7e0c-e003-44f5-ab78-51b462cc5352/usage/162ebcdd-65bd-4087-9f15-3ba9d0355bb8/c0e6ea328bb5c54fabd78228dba135eb966917f8/data/VOM_input/DryRiver/dailyweather.prn",
    "@type": "Usage",
    "@version": 1,
    "entity": {
      "@id": "https://github.com/blob/c0e6ea328bb5c54fabd78228dba135eb966917f8/data/VOM_input/DryRiver/dailyweather.prn"
    },
    "role": "inputs/14"
  },
  {
    "@id": "https://github.com/blob/25ba6a36ab9c5d05b6fed29449e5790183cf3cfe/work/DryRiver/nofreedrainage_cpcff2.0/best",
    "@type": "Entity",
    "@version": 1,
    "checksum": "25ba6a36ab9c5d05b6fed29449e5790183cf3cfe",
    "path": "work/DryRiver/nofreedrainage_cpcff2.0/best"
  },
  {
    "@id": "https://github.com/activities/13fb7e0c-e003-44f5-ab78-51b462cc5352/usage/4bbcd74e-0ef3-41cc-8ec1-e5eddd81cad3/25ba6a36ab9c5d05b6fed29449e5790183cf3cfe/work/DryRiver/nofreedrainage_cpcff2.0/best",
    "@type": "Usage",
    "@version": 1,
    "entity": {
      "@id": "https://github.com/blob/25ba6a36ab9c5d05b6fed29449e5790183cf3cfe/work/DryRiver/nofreedrainage_cpcff2.0/best"
    },
    "role": "inputs/15"
  },
  {
    "@id": "https://github.com/blob/bd3c5efddac4960213fa84574cb05542749b1692/data/DINGO/Ea_dry.txt",
    "@type": "Entity",
    "@version": 1,
    "checksum": "bd3c5efddac4960213fa84574cb05542749b1692",
    "path": "data/DINGO/Ea_dry.txt"
  },
  {
    "@id": "https://github.com/activities/13fb7e0c-e003-44f5-ab78-51b462cc5352/usage/3ad315f0-9c34-42d3-bb2f-351b553d6dd5/bd3c5efddac4960213fa84574cb05542749b1692/data/DINGO/Ea_dry.txt",
    "@type": "Usage",
    "@version": 1,
    "entity": {
      "@id": "https://github.com/blob/bd3c5efddac4960213fa84574cb05542749b1692/data/DINGO/Ea_dry.txt"
    },
    "role": "inputs/17"
  },
  {
    "@id": "https://github.com/blob/1469d0f7c89421496f7fa02caefb167ee431a299/data/DINGO/GPPdaily_dry.txt",
    "@type": "Entity",
    "@version": 1,
    "checksum": "1469d0f7c89421496f7fa02caefb167ee431a299",
    "path": "data/DINGO/GPPdaily_dry.txt"
  },
  {
    "@id": "https://github.com/activities/13fb7e0c-e003-44f5-ab78-51b462cc5352/usage/ff54eb7e-5f08-4afb-8caa-b9600a28ac67/1469d0f7c89421496f7fa02caefb167ee431a299/data/DINGO/GPPdaily_dry.txt",
    "@type": "Usage",
    "@version": 1,
    "entity": {
      "@id": "https://github.com/blob/1469d0f7c89421496f7fa02caefb167ee431a299/data/DINGO/GPPdaily_dry.txt"
    },
    "role": "inputs/19"
  },
  {
    "@id": "https://github.com/blob/cb07aef280eec3fba34f0b52caa53327b4b5be37/data/VOM_output/DryRiver/nofreedrainage_cpcff2.0/sce_out.txt",
    "@type": "Entity",
    "@version": 1,
    "checksum": "cb07aef280eec3fba34f0b52caa53327b4b5be37",
    "path": "data/VOM_output/DryRiver/nofreedrainage_cpcff2.0/sce_out.txt"
  },
  {
    "@id": "https://github.com/activities/13fb7e0c-e003-44f5-ab78-51b462cc5352/usage/50da31ba-75d6-4fb8-a477-3e7edd48bdc7/cb07aef280eec3fba34f0b52caa53327b4b5be37/data/VOM_output/DryRiver/nofreedrainage_cpcff2.0/sce_out.txt",
    "@type": "Usage",
    "@version": 1,
    "entity": {
      "@id": "https://github.com/blob/cb07aef280eec3fba34f0b52caa53327b4b5be37/data/VOM_output/DryRiver/nofreedrainage_cpcff2.0/sce_out.txt"
    },
    "role": "inputs/2"
  },
  {
    "@id": "https://github.com/blob/4ea108b4d60084f8a7b1fdc801630dc6cc98c36d/data/VOM_output/DryRiver/nofreedrainage_cpcff2.0/beststats",
    "@type": "Entity",
    "@version": 1,
    "checksum": "4ea108b4d60084f8a7b1fdc801630dc6cc98c36d",
    "path": "data/VOM_output/DryRiver/nofreedrainage_cpcff2.0/beststats"
  },
  {
    "@id": "https://github.com/activities/13fb7e0c-e003-44f5-ab78-51b462cc5352/generation/3c95503b-31f4-4e3b-b5f1-f44d7add2a64/4ea108b4d60084f8a7b1fdc801630dc6cc98c36d/data/VOM_output/DryRiver/nofreedrainage_cpcff2.0/beststats",
    "@type": "Generation",
    "@version": 1,
    "entity": {
      "@id": "https://github.com/blob/4ea108b4d60084f8a7b1fdc801630dc6cc98c36d/data/VOM_output/DryRiver/nofreedrainage_cpcff2.0/beststats"
    },
    "role": "outputs/3"
  },
  {
    "@id": "https://github.com/activities/13fb7e0c-e003-44f5-ab78-51b462cc5352",
    "@type": "Activity",
    "@version": 1,
    "agents": [
      {
        "@id": "mailto:remko.nijzink@list.lu"
      },
      {
        "@id": "https://github.com/swissdatasciencecenter/renku-python/tree/v0.12.3.dev24"
      }
    ],
    "annotations": null,
    "association": {
      "@id": "https://github.com/activities/13fb7e0c-e003-44f5-ab78-51b462cc5352/association"
    },
    "ended_at_time": "2019-03-23T07:07:31+01:00",
    "generated": [
      {
        "@id": "https://github.com/activities/13fb7e0c-e003-44f5-ab78-51b462cc5352/generation/3c95503b-31f4-4e3b-b5f1-f44d7add2a64/4ea108b4d60084f8a7b1fdc801630dc6cc98c36d/data/VOM_output/DryRiver/nofreedrainage_cpcff2.0/beststats"
      }
    ],
    "invalidated": null,
    "order": 162,
    "qualified_usage": [
      {
        "@id": "https://github.com/activities/13fb7e0c-e003-44f5-ab78-51b462cc5352/usage/7d0ca139-33bb-4e9b-beec-ac57ca7f71aa/c97b3a4e0b6bc81ff62e1e501b285364eaf562e6/src_py/sce_stats.py"
      },
      {
        "@id": "https://github.com/activities/13fb7e0c-e003-44f5-ab78-51b462cc5352/usage/162ebcdd-65bd-4087-9f15-3ba9d0355bb8/c0e6ea328bb5c54fabd78228dba135eb966917f8/data/VOM_input/DryRiver/dailyweather.prn"
      },
      {
        "@id": "https://github.com/activities/13fb7e0c-e003-44f5-ab78-51b462cc5352/usage/4bbcd74e-0ef3-41cc-8ec1-e5eddd81cad3/25ba6a36ab9c5d05b6fed29449e5790183cf3cfe/work/DryRiver/nofreedrainage_cpcff2.0/best"
      },
      {
        "@id": "https://github.com/activities/13fb7e0c-e003-44f5-ab78-51b462cc5352/usage/3ad315f0-9c34-42d3-bb2f-351b553d6dd5/bd3c5efddac4960213fa84574cb05542749b1692/data/DINGO/Ea_dry.txt"
      },
      {
        "@id": "https://github.com/activities/13fb7e0c-e003-44f5-ab78-51b462cc5352/usage/ff54eb7e-5f08-4afb-8caa-b9600a28ac67/1469d0f7c89421496f7fa02caefb167ee431a299/data/DINGO/GPPdaily_dry.txt"
      },
      {
        "@id": "https://github.com/activities/13fb7e0c-e003-44f5-ab78-51b462cc5352/usage/50da31ba-75d6-4fb8-a477-3e7edd48bdc7/cb07aef280eec3fba34f0b52caa53327b4b5be37/data/VOM_output/DryRiver/nofreedrainage_cpcff2.0/sce_out.txt"
      }
    ],
    "started_at_time": "2019-03-22T21:50:08+01:00"
  },
  {
    "@id": "_:2a08ff44d8564cccbaa36e6ed374cdb7",
    "@type": "ActivityCollection",
    "@version": 1,
    "activities": [
      {
        "@id": "https://github.com/activities/13fb7e0c-e003-44f5-ab78-51b462cc5352"
      }
    ]
  }
]