[
  {
    "@id": "mailto:remko.nijzink@list.lu",
    "@type": "Person",
    "@version": 1,
    "affiliation": null,
    "alternate_name": null,
    "email": "remko.nijzink@list.lu",
    "label": "Remko Nijzink",
    "name": "Remko Nijzink"
  },
  {
    "@id": "https://github.com/swissdatasciencecenter/renku-python/tree/v0.13.1.dev1",
    "@type": "SoftwareAgent",
    "@version": 1,
    "label": "renku 0.13.1.dev1"
  },
  {
    "@id": "https://github.com/runs/9690ebdb7ab11b35f8925bd8be90da6d9817e67d/arguments/14",
    "@type": "CommandArgument",
    "@version": 1,
    "label": "Command Argument \"Radn\"",
    "position": 14,
    "prefix": "--var ",
    "value": "Radn"
  },
  {
    "@id": "https://github.com/runs/9690ebdb7ab11b35f8925bd8be90da6d9817e67d/arguments/3",
    "@type": "CommandArgument",
    "@version": 1,
    "label": "Command Argument \"x\"",
    "position": 3,
    "prefix": "-i",
    "value": "x"
  },
  {
    "@id": "https://github.com/runs/9690ebdb7ab11b35f8925bd8be90da6d9817e67d/arguments/8",
    "@type": "CommandArgument",
    "@version": 1,
    "label": "Command Argument \"y\"",
    "position": 8,
    "prefix": "-i",
    "value": "y"
  },
  {
    "@id": "https://github.com/plans/9690ebdb7ab11b35f8925bd8be90da6d9817e67d/outputs/13",
    "@type": "CommandOutputTemplate",
    "@version": 1,
    "create_folder": true,
    "label": "Command Output Template \"data/emp_benchmarks/emp1_gpp_ade\"",
    "mapped_to": null,
    "position": 13,
    "prefix": "-o ",
    "produces": "data/emp_benchmarks/emp1_gpp_ade"
  },
  {
    "@id": "https://github.com/plans/9690ebdb7ab11b35f8925bd8be90da6d9817e67d/inputs/1",
    "@type": "CommandInputTemplate",
    "@version": 1,
    "consumes": "src_py/benchmarking.py",
    "label": "Command Input Template \"src_py/benchmarking.py\"",
    "mapped_to": null,
    "position": 1,
    "prefix": null
  },
  {
    "@id": "https://github.com/plans/9690ebdb7ab11b35f8925bd8be90da6d9817e67d/inputs/10",
    "@type": "CommandInputTemplate",
    "@version": 1,
    "consumes": "data/DINGO/GPPdaily_dry.txt",
    "label": "Command Input Template \"data/DINGO/GPPdaily_dry.txt\"",
    "mapped_to": null,
    "position": 10,
    "prefix": null
  },
  {
    "@id": "https://github.com/plans/9690ebdb7ab11b35f8925bd8be90da6d9817e67d/inputs/11",
    "@type": "CommandInputTemplate",
    "@version": 1,
    "consumes": "data/DINGO/GPPdaily_howard.txt",
    "label": "Command Input Template \"data/DINGO/GPPdaily_howard.txt\"",
    "mapped_to": null,
    "position": 11,
    "prefix": null
  },
  {
    "@id": "https://github.com/plans/9690ebdb7ab11b35f8925bd8be90da6d9817e67d/inputs/12",
    "@type": "CommandInputTemplate",
    "@version": 1,
    "consumes": "data/DINGO/GPPdaily_sturt.txt",
    "label": "Command Input Template \"data/DINGO/GPPdaily_sturt.txt\"",
    "mapped_to": null,
    "position": 12,
    "prefix": null
  },
  {
    "@id": "https://github.com/plans/9690ebdb7ab11b35f8925bd8be90da6d9817e67d/inputs/2",
    "@type": "CommandInputTemplate",
    "@version": 1,
    "consumes": "data/Silo/adelaide.txt",
    "label": "Command Input Template \"data/Silo/adelaide.txt\"",
    "mapped_to": null,
    "position": 2,
    "prefix": "-i "
  },
  {
    "@id": "https://github.com/plans/9690ebdb7ab11b35f8925bd8be90da6d9817e67d/inputs/4",
    "@type": "CommandInputTemplate",
    "@version": 1,
    "consumes": "data/Silo/daly.txt",
    "label": "Command Input Template \"data/Silo/daly.txt\"",
    "mapped_to": null,
    "position": 4,
    "prefix": null
  },
  {
    "@id": "https://github.com/plans/9690ebdb7ab11b35f8925bd8be90da6d9817e67d/inputs/5",
    "@type": "CommandInputTemplate",
    "@version": 1,
    "consumes": "data/Silo/dry.txt",
    "label": "Command Input Template \"data/Silo/dry.txt\"",
    "mapped_to": null,
    "position": 5,
    "prefix": null
  },
  {
    "@id": "https://github.com/plans/9690ebdb7ab11b35f8925bd8be90da6d9817e67d/inputs/6",
    "@type": "CommandInputTemplate",
    "@version": 1,
    "consumes": "data/Silo/howard.txt",
    "label": "Command Input Template \"data/Silo/howard.txt\"",
    "mapped_to": null,
    "position": 6,
    "prefix": null
  },
  {
    "@id": "https://github.com/plans/9690ebdb7ab11b35f8925bd8be90da6d9817e67d/inputs/7",
    "@type": "CommandInputTemplate",
    "@version": 1,
    "consumes": "data/Silo/sturt.txt",
    "label": "Command Input Template \"data/Silo/sturt.txt\"",
    "mapped_to": null,
    "position": 7,
    "prefix": null
  },
  {
    "@id": "https://github.com/plans/9690ebdb7ab11b35f8925bd8be90da6d9817e67d/inputs/9",
    "@type": "CommandInputTemplate",
    "@version": 1,
    "consumes": "data/DINGO/GPPdaily_daly.txt",
    "label": "Command Input Template \"data/DINGO/GPPdaily_daly.txt\"",
    "mapped_to": null,
    "position": 9,
    "prefix": null
  },
  {
    "@id": "https://github.com/plans/9690ebdb7ab11b35f8925bd8be90da6d9817e67d",
    "@type": "Plan",
    "@version": 1,
    "arguments": [
      {
        "@id": "https://github.com/runs/9690ebdb7ab11b35f8925bd8be90da6d9817e67d/arguments/14"
      },
      {
        "@id": "https://github.com/runs/9690ebdb7ab11b35f8925bd8be90da6d9817e67d/arguments/3"
      },
      {
        "@id": "https://github.com/runs/9690ebdb7ab11b35f8925bd8be90da6d9817e67d/arguments/8"
      }
    ],
    "command": "python3",
    "inputs": [
      {
        "@id": "https://github.com/plans/9690ebdb7ab11b35f8925bd8be90da6d9817e67d/inputs/1"
      },
      {
        "@id": "https://github.com/plans/9690ebdb7ab11b35f8925bd8be90da6d9817e67d/inputs/10"
      },
      {
        "@id": "https://github.com/plans/9690ebdb7ab11b35f8925bd8be90da6d9817e67d/inputs/11"
      },
      {
        "@id": "https://github.com/plans/9690ebdb7ab11b35f8925bd8be90da6d9817e67d/inputs/12"
      },
      {
        "@id": "https://github.com/plans/9690ebdb7ab11b35f8925bd8be90da6d9817e67d/inputs/2"
      },
      {
        "@id": "https://github.com/plans/9690ebdb7ab11b35f8925bd8be90da6d9817e67d/inputs/4"
      },
      {
        "@id": "https://github.com/plans/9690ebdb7ab11b35f8925bd8be90da6d9817e67d/inputs/5"
      },
      {
        "@id": "https://github.com/plans/9690ebdb7ab11b35f8925bd8be90da6d9817e67d/inputs/6"
      },
      {
        "@id": "https://github.com/plans/9690ebdb7ab11b35f8925bd8be90da6d9817e67d/inputs/7"
      },
      {
        "@id": "https://github.com/plans/9690ebdb7ab11b35f8925bd8be90da6d9817e67d/inputs/9"
      }
    ],
    "name": "python3-55ee44882b2b46dbbc3bd59d10ba1b99",
    "outputs": [
      {
        "@id": "https://github.com/plans/9690ebdb7ab11b35f8925bd8be90da6d9817e67d/outputs/13"
      }
    ],
    "success_codes": []
  },
  {
    "@id": "https://github.com/swissdatasciencecenter/renku-python/tree/v0.10.5.dev21",
    "@type": "SoftwareAgent",
    "@version": 1,
    "label": "renku 0.10.5.dev21"
  },
  {
    "@id": "https://github.com/activities/4139ed21-0579-42a2-a5d8-b5d334342f73/association",
    "@type": "Association",
    "@version": 1,
    "agent": {
      "@id": "https://github.com/swissdatasciencecenter/renku-python/tree/v0.10.5.dev21"
    },
    "plan": {
      "@id": "https://github.com/plans/9690ebdb7ab11b35f8925bd8be90da6d9817e67d"
    }
  },
  {
    "@id": "https://github.com/blob/850489ada343b9b4a3952bd0f96f9fca33948ca0/src_py/benchmarking.py",
    "@type": "Entity",
    "@version": 1,
    "checksum": "850489ada343b9b4a3952bd0f96f9fca33948ca0",
    "path": "src_py/benchmarking.py"
  },
  {
    "@id": "https://github.com/activities/4139ed21-0579-42a2-a5d8-b5d334342f73/usage/03cbf336-e4dd-4bda-b18b-557226bea069/850489ada343b9b4a3952bd0f96f9fca33948ca0/src_py/benchmarking.py",
    "@type": "Usage",
    "@version": 1,
    "entity": {
      "@id": "https://github.com/blob/850489ada343b9b4a3952bd0f96f9fca33948ca0/src_py/benchmarking.py"
    },
    "role": "inputs/1"
  },
  {
    "@id": "https://github.com/blob/6087874ea4bc046a0e5666a8250873718172f001/data/DINGO/GPPdaily_dry.txt",
    "@type": "Entity",
    "@version": 1,
    "checksum": "6087874ea4bc046a0e5666a8250873718172f001",
    "path": "data/DINGO/GPPdaily_dry.txt"
  },
  {
    "@id": "https://github.com/activities/4139ed21-0579-42a2-a5d8-b5d334342f73/usage/d34b6fad-4165-46d2-9f1e-8ed4da2dfe1f/6087874ea4bc046a0e5666a8250873718172f001/data/DINGO/GPPdaily_dry.txt",
    "@type": "Usage",
    "@version": 1,
    "entity": {
      "@id": "https://github.com/blob/6087874ea4bc046a0e5666a8250873718172f001/data/DINGO/GPPdaily_dry.txt"
    },
    "role": "inputs/10"
  },
  {
    "@id": "https://github.com/blob/816c71deb4ce08123fd44bc32a2b2bec2b2fb498/data/DINGO/GPPdaily_howard.txt",
    "@type": "Entity",
    "@version": 1,
    "checksum": "816c71deb4ce08123fd44bc32a2b2bec2b2fb498",
    "path": "data/DINGO/GPPdaily_howard.txt"
  },
  {
    "@id": "https://github.com/activities/4139ed21-0579-42a2-a5d8-b5d334342f73/usage/d4e6cb3b-e95b-4f18-9109-b9a193a80613/816c71deb4ce08123fd44bc32a2b2bec2b2fb498/data/DINGO/GPPdaily_howard.txt",
    "@type": "Usage",
    "@version": 1,
    "entity": {
      "@id": "https://github.com/blob/816c71deb4ce08123fd44bc32a2b2bec2b2fb498/data/DINGO/GPPdaily_howard.txt"
    },
    "role": "inputs/11"
  },
  {
    "@id": "https://github.com/blob/a2d11674e62070211833a18733a4dff866f175a5/data/DINGO/GPPdaily_sturt.txt",
    "@type": "Entity",
    "@version": 1,
    "checksum": "a2d11674e62070211833a18733a4dff866f175a5",
    "path": "data/DINGO/GPPdaily_sturt.txt"
  },
  {
    "@id": "https://github.com/activities/4139ed21-0579-42a2-a5d8-b5d334342f73/usage/0b498153-81cd-45d7-85d7-06f2bab06330/a2d11674e62070211833a18733a4dff866f175a5/data/DINGO/GPPdaily_sturt.txt",
    "@type": "Usage",
    "@version": 1,
    "entity": {
      "@id": "https://github.com/blob/a2d11674e62070211833a18733a4dff866f175a5/data/DINGO/GPPdaily_sturt.txt"
    },
    "role": "inputs/12"
  },
  {
    "@id": "https://github.com/blob/8a47f2f56b17b58466836be778d83582d02c8601/data/Silo/adelaide.txt",
    "@type": "Entity",
    "@version": 1,
    "checksum": "8a47f2f56b17b58466836be778d83582d02c8601",
    "path": "data/Silo/adelaide.txt"
  },
  {
    "@id": "https://github.com/activities/4139ed21-0579-42a2-a5d8-b5d334342f73/usage/4713f821-f878-40c9-aca4-9f4c24b55bfd/8a47f2f56b17b58466836be778d83582d02c8601/data/Silo/adelaide.txt",
    "@type": "Usage",
    "@version": 1,
    "entity": {
      "@id": "https://github.com/blob/8a47f2f56b17b58466836be778d83582d02c8601/data/Silo/adelaide.txt"
    },
    "role": "inputs/2"
  },
  {
    "@id": "https://github.com/blob/7980b54d0005e8f0e2ac4f8fcd95ffb2fb2380e4/data/Silo/daly.txt",
    "@type": "Entity",
    "@version": 1,
    "checksum": "7980b54d0005e8f0e2ac4f8fcd95ffb2fb2380e4",
    "path": "data/Silo/daly.txt"
  },
  {
    "@id": "https://github.com/activities/4139ed21-0579-42a2-a5d8-b5d334342f73/usage/e7c422c1-efb2-4020-aa0e-40094aafb0b2/7980b54d0005e8f0e2ac4f8fcd95ffb2fb2380e4/data/Silo/daly.txt",
    "@type": "Usage",
    "@version": 1,
    "entity": {
      "@id": "https://github.com/blob/7980b54d0005e8f0e2ac4f8fcd95ffb2fb2380e4/data/Silo/daly.txt"
    },
    "role": "inputs/4"
  },
  {
    "@id": "https://github.com/blob/23ab93f20e8366b5e55603ea99f7bdad67db5fb9/data/Silo/dry.txt",
    "@type": "Entity",
    "@version": 1,
    "checksum": "23ab93f20e8366b5e55603ea99f7bdad67db5fb9",
    "path": "data/Silo/dry.txt"
  },
  {
    "@id": "https://github.com/activities/4139ed21-0579-42a2-a5d8-b5d334342f73/usage/cf16e1e6-7bc8-41bd-af20-470611821847/23ab93f20e8366b5e55603ea99f7bdad67db5fb9/data/Silo/dry.txt",
    "@type": "Usage",
    "@version": 1,
    "entity": {
      "@id": "https://github.com/blob/23ab93f20e8366b5e55603ea99f7bdad67db5fb9/data/Silo/dry.txt"
    },
    "role": "inputs/5"
  },
  {
    "@id": "https://github.com/blob/8ba21415289aefd2aa088b35af093abc5213fcf9/data/Silo/howard.txt",
    "@type": "Entity",
    "@version": 1,
    "checksum": "8ba21415289aefd2aa088b35af093abc5213fcf9",
    "path": "data/Silo/howard.txt"
  },
  {
    "@id": "https://github.com/activities/4139ed21-0579-42a2-a5d8-b5d334342f73/usage/aa32b54d-0d2b-4812-9e45-5b5cc7453220/8ba21415289aefd2aa088b35af093abc5213fcf9/data/Silo/howard.txt",
    "@type": "Usage",
    "@version": 1,
    "entity": {
      "@id": "https://github.com/blob/8ba21415289aefd2aa088b35af093abc5213fcf9/data/Silo/howard.txt"
    },
    "role": "inputs/6"
  },
  {
    "@id": "https://github.com/blob/6f0ee95210eb831f773f4c5e0a5b59eee4e37b31/data/Silo/sturt.txt",
    "@type": "Entity",
    "@version": 1,
    "checksum": "6f0ee95210eb831f773f4c5e0a5b59eee4e37b31",
    "path": "data/Silo/sturt.txt"
  },
  {
    "@id": "https://github.com/activities/4139ed21-0579-42a2-a5d8-b5d334342f73/usage/612e8bd7-753a-4efd-9596-26f418b1feee/6f0ee95210eb831f773f4c5e0a5b59eee4e37b31/data/Silo/sturt.txt",
    "@type": "Usage",
    "@version": 1,
    "entity": {
      "@id": "https://github.com/blob/6f0ee95210eb831f773f4c5e0a5b59eee4e37b31/data/Silo/sturt.txt"
    },
    "role": "inputs/7"
  },
  {
    "@id": "https://github.com/blob/4f5e1b56382fac1aae42b65e1e5446be48551a37/data/DINGO/GPPdaily_daly.txt",
    "@type": "Entity",
    "@version": 1,
    "checksum": "4f5e1b56382fac1aae42b65e1e5446be48551a37",
    "path": "data/DINGO/GPPdaily_daly.txt"
  },
  {
    "@id": "https://github.com/activities/4139ed21-0579-42a2-a5d8-b5d334342f73/usage/b4d7ea90-6583-4990-b1f3-18f00f0b91de/4f5e1b56382fac1aae42b65e1e5446be48551a37/data/DINGO/GPPdaily_daly.txt",
    "@type": "Usage",
    "@version": 1,
    "entity": {
      "@id": "https://github.com/blob/4f5e1b56382fac1aae42b65e1e5446be48551a37/data/DINGO/GPPdaily_daly.txt"
    },
    "role": "inputs/9"
  },
  {
    "@id": "https://github.com/blob/f091743e6bc4289b6a50287929211b02d5ad3204/data/emp_benchmarks/emp1_gpp_ade",
    "@type": "Entity",
    "@version": 1,
    "checksum": "f091743e6bc4289b6a50287929211b02d5ad3204",
    "path": "data/emp_benchmarks/emp1_gpp_ade"
  },
  {
    "@id": "https://github.com/activities/4139ed21-0579-42a2-a5d8-b5d334342f73/generation/a6dd78ea-1897-4906-9194-97c061927136/f091743e6bc4289b6a50287929211b02d5ad3204/data/emp_benchmarks/emp1_gpp_ade",
    "@type": "Generation",
    "@version": 1,
    "entity": {
      "@id": "https://github.com/blob/f091743e6bc4289b6a50287929211b02d5ad3204/data/emp_benchmarks/emp1_gpp_ade"
    },
    "role": "outputs/13"
  },
  {
    "@id": "https://github.com/activities/4139ed21-0579-42a2-a5d8-b5d334342f73",
    "@type": "Activity",
    "@version": 1,
    "agents": [
      {
        "@id": "mailto:remko.nijzink@list.lu"
      },
      {
        "@id": "https://github.com/swissdatasciencecenter/renku-python/tree/v0.13.1.dev1"
      }
    ],
    "annotations": null,
    "association": {
      "@id": "https://github.com/activities/4139ed21-0579-42a2-a5d8-b5d334342f73/association"
    },
    "ended_at_time": "2020-11-19T10:03:19+01:00",
    "generated": [
      {
        "@id": "https://github.com/activities/4139ed21-0579-42a2-a5d8-b5d334342f73/generation/a6dd78ea-1897-4906-9194-97c061927136/f091743e6bc4289b6a50287929211b02d5ad3204/data/emp_benchmarks/emp1_gpp_ade"
      }
    ],
    "invalidated": null,
    "order": 9577,
    "qualified_usage": [
      {
        "@id": "https://github.com/activities/4139ed21-0579-42a2-a5d8-b5d334342f73/usage/03cbf336-e4dd-4bda-b18b-557226bea069/850489ada343b9b4a3952bd0f96f9fca33948ca0/src_py/benchmarking.py"
      },
      {
        "@id": "https://github.com/activities/4139ed21-0579-42a2-a5d8-b5d334342f73/usage/d34b6fad-4165-46d2-9f1e-8ed4da2dfe1f/6087874ea4bc046a0e5666a8250873718172f001/data/DINGO/GPPdaily_dry.txt"
      },
      {
        "@id": "https://github.com/activities/4139ed21-0579-42a2-a5d8-b5d334342f73/usage/d4e6cb3b-e95b-4f18-9109-b9a193a80613/816c71deb4ce08123fd44bc32a2b2bec2b2fb498/data/DINGO/GPPdaily_howard.txt"
      },
      {
        "@id": "https://github.com/activities/4139ed21-0579-42a2-a5d8-b5d334342f73/usage/0b498153-81cd-45d7-85d7-06f2bab06330/a2d11674e62070211833a18733a4dff866f175a5/data/DINGO/GPPdaily_sturt.txt"
      },
      {
        "@id": "https://github.com/activities/4139ed21-0579-42a2-a5d8-b5d334342f73/usage/4713f821-f878-40c9-aca4-9f4c24b55bfd/8a47f2f56b17b58466836be778d83582d02c8601/data/Silo/adelaide.txt"
      },
      {
        "@id": "https://github.com/activities/4139ed21-0579-42a2-a5d8-b5d334342f73/usage/e7c422c1-efb2-4020-aa0e-40094aafb0b2/7980b54d0005e8f0e2ac4f8fcd95ffb2fb2380e4/data/Silo/daly.txt"
      },
      {
        "@id": "https://github.com/activities/4139ed21-0579-42a2-a5d8-b5d334342f73/usage/cf16e1e6-7bc8-41bd-af20-470611821847/23ab93f20e8366b5e55603ea99f7bdad67db5fb9/data/Silo/dry.txt"
      },
      {
        "@id": "https://github.com/activities/4139ed21-0579-42a2-a5d8-b5d334342f73/usage/aa32b54d-0d2b-4812-9e45-5b5cc7453220/8ba21415289aefd2aa088b35af093abc5213fcf9/data/Silo/howard.txt"
      },
      {
        "@id": "https://github.com/activities/4139ed21-0579-42a2-a5d8-b5d334342f73/usage/612e8bd7-753a-4efd-9596-26f418b1feee/6f0ee95210eb831f773f4c5e0a5b59eee4e37b31/data/Silo/sturt.txt"
      },
      {
        "@id": "https://github.com/activities/4139ed21-0579-42a2-a5d8-b5d334342f73/usage/b4d7ea90-6583-4990-b1f3-18f00f0b91de/4f5e1b56382fac1aae42b65e1e5446be48551a37/data/DINGO/GPPdaily_daly.txt"
      }
    ],
    "started_at_time": "2020-11-19T10:03:19+01:00"
  },
  {
    "@id": "_:d1978ff6b0e643549e372c2e0d27fffe",
    "@type": "ActivityCollection",
    "@version": 1,
    "activities": [
      {
        "@id": "https://github.com/activities/4139ed21-0579-42a2-a5d8-b5d334342f73"
      }
    ]
  }
]