[
  {
    "@id": "mailto:remko.nijzink@list.lu",
    "@type": "Person",
    "@version": 1,
    "affiliation": null,
    "alternate_name": null,
    "email": "remko.nijzink@list.lu",
    "label": "Remko Nijzink",
    "name": "Remko Nijzink"
  },
  {
    "@id": "https://github.com/swissdatasciencecenter/renku-python/tree/v0.12.3.dev23",
    "@type": "SoftwareAgent",
    "@version": 1,
    "label": "renku 0.12.3.dev23"
  },
  {
    "@id": "https://github.com/runs/d992f814f584e5802315e49476475c106cc2e7a1/arguments/11",
    "@type": "CommandArgument",
    "@version": 1,
    "label": "Command Argument \"5\"",
    "position": 11,
    "prefix": "-s ",
    "value": "5"
  },
  {
    "@id": "https://github.com/runs/d992f814f584e5802315e49476475c106cc2e7a1/arguments/12",
    "@type": "CommandArgument",
    "@version": 1,
    "label": "Command Argument \"9\"",
    "position": 12,
    "prefix": "-e ",
    "value": "9"
  },
  {
    "@id": "https://github.com/runs/d992f814f584e5802315e49476475c106cc2e7a1/arguments/13",
    "@type": "CommandArgument",
    "@version": 1,
    "label": "Command Argument \"w\"",
    "position": 13,
    "prefix": "-s",
    "value": "w"
  },
  {
    "@id": "https://github.com/runs/d992f814f584e5802315e49476475c106cc2e7a1/arguments/14",
    "@type": "CommandArgument",
    "@version": 1,
    "label": "Command Argument \"12\"",
    "position": 14,
    "prefix": null,
    "value": "12"
  },
  {
    "@id": "https://github.com/runs/d992f814f584e5802315e49476475c106cc2e7a1/arguments/15",
    "@type": "CommandArgument",
    "@version": 1,
    "label": "Command Argument \"w\"",
    "position": 15,
    "prefix": "-e",
    "value": "w"
  },
  {
    "@id": "https://github.com/runs/d992f814f584e5802315e49476475c106cc2e7a1/arguments/16",
    "@type": "CommandArgument",
    "@version": 1,
    "label": "Command Argument \"3\"",
    "position": 16,
    "prefix": null,
    "value": "3"
  },
  {
    "@id": "https://github.com/runs/d992f814f584e5802315e49476475c106cc2e7a1/arguments/3",
    "@type": "CommandArgument",
    "@version": 1,
    "label": "Command Argument \"o\"",
    "position": 3,
    "prefix": "-e",
    "value": "o"
  },
  {
    "@id": "https://github.com/runs/d992f814f584e5802315e49476475c106cc2e7a1/arguments/5",
    "@type": "CommandArgument",
    "@version": 1,
    "label": "Command Argument \"o\"",
    "position": 5,
    "prefix": "-a",
    "value": "o"
  },
  {
    "@id": "https://github.com/runs/d992f814f584e5802315e49476475c106cc2e7a1/arguments/7",
    "@type": "CommandArgument",
    "@version": 1,
    "label": "Command Argument \"o\"",
    "position": 7,
    "prefix": "-p",
    "value": "o"
  },
  {
    "@id": "https://github.com/runs/d992f814f584e5802315e49476475c106cc2e7a1/arguments/9",
    "@type": "CommandArgument",
    "@version": 1,
    "label": "Command Argument \"d\"",
    "position": 9,
    "prefix": "-p",
    "value": "d"
  },
  {
    "@id": "https://github.com/plans/d992f814f584e5802315e49476475c106cc2e7a1/outputs/17",
    "@type": "CommandOutputTemplate",
    "@version": 1,
    "create_folder": true,
    "label": "Command Output Template \"data/VOM_output/HowardSprings/freedrainage_cpcff1.2/sce_stats_best\"",
    "mapped_to": null,
    "position": 17,
    "prefix": "-o ",
    "produces": "data/VOM_output/HowardSprings/freedrainage_cpcff1.2/sce_stats_best"
  },
  {
    "@id": "https://github.com/plans/d992f814f584e5802315e49476475c106cc2e7a1/inputs/1",
    "@type": "CommandInputTemplate",
    "@version": 1,
    "consumes": "src_py/sce_stats_best.py",
    "label": "Command Input Template \"src_py/sce_stats_best.py\"",
    "mapped_to": null,
    "position": 1,
    "prefix": null
  },
  {
    "@id": "https://github.com/plans/d992f814f584e5802315e49476475c106cc2e7a1/inputs/10",
    "@type": "CommandInputTemplate",
    "@version": 1,
    "consumes": "data/fPAR/dates_v5",
    "label": "Command Input Template \"data/fPAR/dates_v5\"",
    "mapped_to": null,
    "position": 10,
    "prefix": null
  },
  {
    "@id": "https://github.com/plans/d992f814f584e5802315e49476475c106cc2e7a1/inputs/2",
    "@type": "CommandInputTemplate",
    "@version": 1,
    "consumes": "data/VOM_output/HowardSprings/freedrainage_cpcff1.2/sce_best/results_daily.txt",
    "label": "Command Input Template \"data/VOM_output/HowardSprings/freedrainage_cpcff1.2/sce_best/results_daily.txt\"",
    "mapped_to": null,
    "position": 2,
    "prefix": "-i "
  },
  {
    "@id": "https://github.com/plans/d992f814f584e5802315e49476475c106cc2e7a1/inputs/4",
    "@type": "CommandInputTemplate",
    "@version": 1,
    "consumes": "data/DINGO/Ea_howard.txt",
    "label": "Command Input Template \"data/DINGO/Ea_howard.txt\"",
    "mapped_to": null,
    "position": 4,
    "prefix": null
  },
  {
    "@id": "https://github.com/plans/d992f814f584e5802315e49476475c106cc2e7a1/inputs/6",
    "@type": "CommandInputTemplate",
    "@version": 1,
    "consumes": "data/DINGO/GPPdaily_howard.txt",
    "label": "Command Input Template \"data/DINGO/GPPdaily_howard.txt\"",
    "mapped_to": null,
    "position": 6,
    "prefix": null
  },
  {
    "@id": "https://github.com/plans/d992f814f584e5802315e49476475c106cc2e7a1/inputs/8",
    "@type": "CommandInputTemplate",
    "@version": 1,
    "consumes": "data/fPAR/fpar_howard_v5.txt",
    "label": "Command Input Template \"data/fPAR/fpar_howard_v5.txt\"",
    "mapped_to": null,
    "position": 8,
    "prefix": null
  },
  {
    "@id": "https://github.com/plans/d992f814f584e5802315e49476475c106cc2e7a1",
    "@type": "Plan",
    "@version": 1,
    "arguments": [
      {
        "@id": "https://github.com/runs/d992f814f584e5802315e49476475c106cc2e7a1/arguments/11"
      },
      {
        "@id": "https://github.com/runs/d992f814f584e5802315e49476475c106cc2e7a1/arguments/12"
      },
      {
        "@id": "https://github.com/runs/d992f814f584e5802315e49476475c106cc2e7a1/arguments/13"
      },
      {
        "@id": "https://github.com/runs/d992f814f584e5802315e49476475c106cc2e7a1/arguments/14"
      },
      {
        "@id": "https://github.com/runs/d992f814f584e5802315e49476475c106cc2e7a1/arguments/15"
      },
      {
        "@id": "https://github.com/runs/d992f814f584e5802315e49476475c106cc2e7a1/arguments/16"
      },
      {
        "@id": "https://github.com/runs/d992f814f584e5802315e49476475c106cc2e7a1/arguments/3"
      },
      {
        "@id": "https://github.com/runs/d992f814f584e5802315e49476475c106cc2e7a1/arguments/5"
      },
      {
        "@id": "https://github.com/runs/d992f814f584e5802315e49476475c106cc2e7a1/arguments/7"
      },
      {
        "@id": "https://github.com/runs/d992f814f584e5802315e49476475c106cc2e7a1/arguments/9"
      }
    ],
    "command": "python3",
    "inputs": [
      {
        "@id": "https://github.com/plans/d992f814f584e5802315e49476475c106cc2e7a1/inputs/1"
      },
      {
        "@id": "https://github.com/plans/d992f814f584e5802315e49476475c106cc2e7a1/inputs/10"
      },
      {
        "@id": "https://github.com/plans/d992f814f584e5802315e49476475c106cc2e7a1/inputs/2"
      },
      {
        "@id": "https://github.com/plans/d992f814f584e5802315e49476475c106cc2e7a1/inputs/4"
      },
      {
        "@id": "https://github.com/plans/d992f814f584e5802315e49476475c106cc2e7a1/inputs/6"
      },
      {
        "@id": "https://github.com/plans/d992f814f584e5802315e49476475c106cc2e7a1/inputs/8"
      }
    ],
    "name": "python3-9eca8668e6b043ab93eb9b092e723a61",
    "outputs": [
      {
        "@id": "https://github.com/plans/d992f814f584e5802315e49476475c106cc2e7a1/outputs/17"
      }
    ],
    "success_codes": []
  },
  {
    "@id": "https://github.com/swissdatasciencecenter/renku-python/tree/v0.8.3.dev23",
    "@type": "SoftwareAgent",
    "@version": 1,
    "label": "renku 0.8.3.dev23"
  },
  {
    "@id": "https://github.com/activities/15dc4ed5-08ac-43f3-9057-b1c175b1f87d/association",
    "@type": "Association",
    "@version": 1,
    "agent": {
      "@id": "https://github.com/swissdatasciencecenter/renku-python/tree/v0.8.3.dev23"
    },
    "plan": {
      "@id": "https://github.com/plans/d992f814f584e5802315e49476475c106cc2e7a1"
    }
  },
  {
    "@id": "https://github.com/blob/c44077ab947b3904b8b3412abe231f3efba037e7/src_py/sce_stats_best.py",
    "@type": "Entity",
    "@version": 1,
    "checksum": "c44077ab947b3904b8b3412abe231f3efba037e7",
    "path": "src_py/sce_stats_best.py"
  },
  {
    "@id": "https://github.com/activities/15dc4ed5-08ac-43f3-9057-b1c175b1f87d/usage/ac634fc1-8222-4237-b06c-0de4d95be4e0/c44077ab947b3904b8b3412abe231f3efba037e7/src_py/sce_stats_best.py",
    "@type": "Usage",
    "@version": 1,
    "entity": {
      "@id": "https://github.com/blob/c44077ab947b3904b8b3412abe231f3efba037e7/src_py/sce_stats_best.py"
    },
    "role": "inputs/1"
  },
  {
    "@id": "https://github.com/blob/b40288587bcbc5d23f665bcd3ae96a45349e4623/data/fPAR/dates_v5",
    "@type": "Entity",
    "@version": 1,
    "checksum": "b40288587bcbc5d23f665bcd3ae96a45349e4623",
    "path": "data/fPAR/dates_v5"
  },
  {
    "@id": "https://github.com/activities/15dc4ed5-08ac-43f3-9057-b1c175b1f87d/usage/1a8c6028-9733-4784-80e4-48ab4f9c702c/b40288587bcbc5d23f665bcd3ae96a45349e4623/data/fPAR/dates_v5",
    "@type": "Usage",
    "@version": 1,
    "entity": {
      "@id": "https://github.com/blob/b40288587bcbc5d23f665bcd3ae96a45349e4623/data/fPAR/dates_v5"
    },
    "role": "inputs/10"
  },
  {
    "@id": "https://github.com/blob/146841b4f8aa820fdfcaabca5fb5787a3eaff777/data/VOM_output/HowardSprings/freedrainage_cpcff1.2/sce_best/results_daily.txt",
    "@type": "Entity",
    "@version": 1,
    "checksum": "146841b4f8aa820fdfcaabca5fb5787a3eaff777",
    "path": "data/VOM_output/HowardSprings/freedrainage_cpcff1.2/sce_best/results_daily.txt"
  },
  {
    "@id": "https://github.com/activities/15dc4ed5-08ac-43f3-9057-b1c175b1f87d/usage/5a5fa60d-2eb1-48a9-81dc-fc508a3c34fa/146841b4f8aa820fdfcaabca5fb5787a3eaff777/data/VOM_output/HowardSprings/freedrainage_cpcff1.2/sce_best/results_daily.txt",
    "@type": "Usage",
    "@version": 1,
    "entity": {
      "@id": "https://github.com/blob/146841b4f8aa820fdfcaabca5fb5787a3eaff777/data/VOM_output/HowardSprings/freedrainage_cpcff1.2/sce_best/results_daily.txt"
    },
    "role": "inputs/2"
  },
  {
    "@id": "https://github.com/blob/402fa03e1947f7f371795fc820f85bf978c3a5ec/data/DINGO/Ea_howard.txt",
    "@type": "Entity",
    "@version": 1,
    "checksum": "402fa03e1947f7f371795fc820f85bf978c3a5ec",
    "path": "data/DINGO/Ea_howard.txt"
  },
  {
    "@id": "https://github.com/activities/15dc4ed5-08ac-43f3-9057-b1c175b1f87d/usage/0047a257-790e-4f01-9fe8-1ccae4b08a82/402fa03e1947f7f371795fc820f85bf978c3a5ec/data/DINGO/Ea_howard.txt",
    "@type": "Usage",
    "@version": 1,
    "entity": {
      "@id": "https://github.com/blob/402fa03e1947f7f371795fc820f85bf978c3a5ec/data/DINGO/Ea_howard.txt"
    },
    "role": "inputs/4"
  },
  {
    "@id": "https://github.com/blob/f9b3ac0ed05be7922b93ff96a5d9cce0de1d610b/data/DINGO/GPPdaily_howard.txt",
    "@type": "Entity",
    "@version": 1,
    "checksum": "f9b3ac0ed05be7922b93ff96a5d9cce0de1d610b",
    "path": "data/DINGO/GPPdaily_howard.txt"
  },
  {
    "@id": "https://github.com/activities/15dc4ed5-08ac-43f3-9057-b1c175b1f87d/usage/1e5d4b3b-dd50-4247-9e74-c4471a3893cb/f9b3ac0ed05be7922b93ff96a5d9cce0de1d610b/data/DINGO/GPPdaily_howard.txt",
    "@type": "Usage",
    "@version": 1,
    "entity": {
      "@id": "https://github.com/blob/f9b3ac0ed05be7922b93ff96a5d9cce0de1d610b/data/DINGO/GPPdaily_howard.txt"
    },
    "role": "inputs/6"
  },
  {
    "@id": "https://github.com/blob/872032e88ed03924db2ecb6937815494ac59f14c/data/fPAR/fpar_howard_v5.txt",
    "@type": "Entity",
    "@version": 1,
    "checksum": "872032e88ed03924db2ecb6937815494ac59f14c",
    "path": "data/fPAR/fpar_howard_v5.txt"
  },
  {
    "@id": "https://github.com/activities/15dc4ed5-08ac-43f3-9057-b1c175b1f87d/usage/d2c69b23-6dca-46fd-a71b-b4643f91ea9e/872032e88ed03924db2ecb6937815494ac59f14c/data/fPAR/fpar_howard_v5.txt",
    "@type": "Usage",
    "@version": 1,
    "entity": {
      "@id": "https://github.com/blob/872032e88ed03924db2ecb6937815494ac59f14c/data/fPAR/fpar_howard_v5.txt"
    },
    "role": "inputs/8"
  },
  {
    "@id": "https://github.com/blob/04ec74077dd1a6a078b5e6c75ffb7f6542567e82/data/VOM_output/HowardSprings/freedrainage_cpcff1.2/sce_stats_best/pc_beststats.txt",
    "@type": "Entity",
    "@version": 1,
    "checksum": "04ec74077dd1a6a078b5e6c75ffb7f6542567e82",
    "path": "data/VOM_output/HowardSprings/freedrainage_cpcff1.2/sce_stats_best/pc_beststats.txt"
  },
  {
    "@id": "https://github.com/blob/72d39b8714b1d04f0deb3da889ac894eeebf4a15/data/VOM_output/HowardSprings/freedrainage_cpcff1.2/sce_stats_best/ass_beststats.txt",
    "@type": "Entity",
    "@version": 1,
    "checksum": "72d39b8714b1d04f0deb3da889ac894eeebf4a15",
    "path": "data/VOM_output/HowardSprings/freedrainage_cpcff1.2/sce_stats_best/ass_beststats.txt"
  },
  {
    "@id": "https://github.com/blob/c26770150492b36dbbbd397efb481b20207da35e/data/VOM_output/HowardSprings/freedrainage_cpcff1.2/sce_stats_best/evap_beststats.txt",
    "@type": "Entity",
    "@version": 1,
    "checksum": "c26770150492b36dbbbd397efb481b20207da35e",
    "path": "data/VOM_output/HowardSprings/freedrainage_cpcff1.2/sce_stats_best/evap_beststats.txt"
  },
  {
    "@id": "https://github.com/blob/0ab73def8cb07e5663e751741d48d49d9e4f1bf8/data/VOM_output/HowardSprings/freedrainage_cpcff1.2/sce_stats_best",
    "@type": "Collection",
    "@version": 1,
    "checksum": "0ab73def8cb07e5663e751741d48d49d9e4f1bf8",
    "members": [
      {
        "@id": "https://github.com/blob/04ec74077dd1a6a078b5e6c75ffb7f6542567e82/data/VOM_output/HowardSprings/freedrainage_cpcff1.2/sce_stats_best/pc_beststats.txt"
      },
      {
        "@id": "https://github.com/blob/72d39b8714b1d04f0deb3da889ac894eeebf4a15/data/VOM_output/HowardSprings/freedrainage_cpcff1.2/sce_stats_best/ass_beststats.txt"
      },
      {
        "@id": "https://github.com/blob/c26770150492b36dbbbd397efb481b20207da35e/data/VOM_output/HowardSprings/freedrainage_cpcff1.2/sce_stats_best/evap_beststats.txt"
      }
    ],
    "path": "data/VOM_output/HowardSprings/freedrainage_cpcff1.2/sce_stats_best"
  },
  {
    "@id": "https://github.com/activities/15dc4ed5-08ac-43f3-9057-b1c175b1f87d/generation/69fef321-5870-45d6-b0c2-8566b5610cf4/0ab73def8cb07e5663e751741d48d49d9e4f1bf8/data/VOM_output/HowardSprings/freedrainage_cpcff1.2/sce_stats_best",
    "@type": "Generation",
    "@version": 1,
    "entity": {
      "@id": "https://github.com/blob/0ab73def8cb07e5663e751741d48d49d9e4f1bf8/data/VOM_output/HowardSprings/freedrainage_cpcff1.2/sce_stats_best"
    },
    "role": "outputs/17"
  },
  {
    "@id": "https://github.com/activities/15dc4ed5-08ac-43f3-9057-b1c175b1f87d",
    "@type": "Activity",
    "@version": 1,
    "agents": [
      {
        "@id": "mailto:remko.nijzink@list.lu"
      },
      {
        "@id": "https://github.com/swissdatasciencecenter/renku-python/tree/v0.12.3.dev23"
      }
    ],
    "annotations": null,
    "association": {
      "@id": "https://github.com/activities/15dc4ed5-08ac-43f3-9057-b1c175b1f87d/association"
    },
    "ended_at_time": "2020-02-18T08:41:02+01:00",
    "generated": [
      {
        "@id": "https://github.com/activities/15dc4ed5-08ac-43f3-9057-b1c175b1f87d/generation/69fef321-5870-45d6-b0c2-8566b5610cf4/0ab73def8cb07e5663e751741d48d49d9e4f1bf8/data/VOM_output/HowardSprings/freedrainage_cpcff1.2/sce_stats_best"
      }
    ],
    "invalidated": null,
    "order": 7983,
    "qualified_usage": [
      {
        "@id": "https://github.com/activities/15dc4ed5-08ac-43f3-9057-b1c175b1f87d/usage/ac634fc1-8222-4237-b06c-0de4d95be4e0/c44077ab947b3904b8b3412abe231f3efba037e7/src_py/sce_stats_best.py"
      },
      {
        "@id": "https://github.com/activities/15dc4ed5-08ac-43f3-9057-b1c175b1f87d/usage/1a8c6028-9733-4784-80e4-48ab4f9c702c/b40288587bcbc5d23f665bcd3ae96a45349e4623/data/fPAR/dates_v5"
      },
      {
        "@id": "https://github.com/activities/15dc4ed5-08ac-43f3-9057-b1c175b1f87d/usage/5a5fa60d-2eb1-48a9-81dc-fc508a3c34fa/146841b4f8aa820fdfcaabca5fb5787a3eaff777/data/VOM_output/HowardSprings/freedrainage_cpcff1.2/sce_best/results_daily.txt"
      },
      {
        "@id": "https://github.com/activities/15dc4ed5-08ac-43f3-9057-b1c175b1f87d/usage/0047a257-790e-4f01-9fe8-1ccae4b08a82/402fa03e1947f7f371795fc820f85bf978c3a5ec/data/DINGO/Ea_howard.txt"
      },
      {
        "@id": "https://github.com/activities/15dc4ed5-08ac-43f3-9057-b1c175b1f87d/usage/1e5d4b3b-dd50-4247-9e74-c4471a3893cb/f9b3ac0ed05be7922b93ff96a5d9cce0de1d610b/data/DINGO/GPPdaily_howard.txt"
      },
      {
        "@id": "https://github.com/activities/15dc4ed5-08ac-43f3-9057-b1c175b1f87d/usage/d2c69b23-6dca-46fd-a71b-b4643f91ea9e/872032e88ed03924db2ecb6937815494ac59f14c/data/fPAR/fpar_howard_v5.txt"
      }
    ],
    "started_at_time": "2020-02-18T08:41:02+01:00"
  },
  {
    "@id": "_:e2e16f9aa7bc4f2db32f9eb8982072cf",
    "@type": "ActivityCollection",
    "@version": 1,
    "activities": [
      {
        "@id": "https://github.com/activities/15dc4ed5-08ac-43f3-9057-b1c175b1f87d"
      }
    ]
  }
]